deocr/__init__.py
deocr/cli.py
deocr/engine/args.py
deocr/engine/dataio.py
deocr/engine/defaults.py
deocr/engine/playwright/async_api.py
deocr/engine/playwright/md2html.py
deocr/engine/playwright/pdf2image.py
deocr/engine/playwright/sync_api.py
deocr/load.py
deocr-0.3.2.dist-info/licenses/LICENSE
deocr-0.3.2.dist-info/WHEEL
deocr-0.3.2.dist-info/METADATA
deocr-0.3.2.dist-info/RECORD
