Metadata-Version: 2.4
Name: DeOCR
Version: 0.3.2
Summary: A high-performance highly-customizable reverse OCR tool that renders text or huggingface-compatible datasets to images. Dimension, DPI, CSS configurable!
Author: Moenupa
Author-email: Moenupa <moenupa@gmail.com>
License-Expression: MIT
License-File: LICENSE
Classifier: Programming Language :: Python :: 3
Classifier: Operating System :: OS Independent
Requires-Dist: jsonargparse[signatures]>=4.26.1
Requires-Dist: datasets[vision]
Requires-Dist: markdown-it-py>=3.0.0
Requires-Dist: linkify-it-py
Requires-Dist: playwright>=1.49.1,<1.56.0 ; extra == 'playwright'
Requires-Dist: pymupdf ; extra == 'pymupdf'
Requires-Dist: reportlab>=4.4.4 ; extra == 'reportlab'
Requires-Python: >=3.9, <3.15
Project-URL: Homepage, https://github.com/Moenupa/DeOCR
Project-URL: Issues, https://github.com/Moenupa/DeOCR/issues
Provides-Extra: playwright
Provides-Extra: pymupdf
Provides-Extra: reportlab
